reddit_consensus/__init__.py
reddit_consensus/__main__.py
reddit_consensus/agent_state.py
reddit_consensus/cli.py
reddit_consensus/colors.py
reddit_consensus/config.py
reddit_consensus/prompts.py
reddit_consensus/recommender.py
reddit_consensus/tools.py
reddit_consensus/validate_config.py
reddit_consensus-0.1.2.dist-info/licenses/LICENSE
reddit_consensus-0.1.2.dist-info/METADATA
reddit_consensus-0.1.2.dist-info/WHEEL
reddit_consensus-0.1.2.dist-info/entry_points.txt
reddit_consensus-0.1.2.dist-info/top_level.txt
reddit_consensus-0.1.2.dist-info/RECORD
