Metadata-Version: 2.4
Name: reddit-consensus
Version: 0.1.2
Summary: Autonomous AI agent for tasteful recommendations via Reddit community analysis
Author-email: Jash Vira <jashvira2001404@gmail.com>
Maintainer-email: Jash Vira <jashvira2001404@gmail.com>
License-Expression: MIT
Project-URL: Homepage, https://github.com/jashvira/reddit-consensus
Project-URL: Repository, https://github.com/jashvira/reddit-consensus.git
Project-URL: Documentation, https://github.com/jashvira/reddit-consensus#readme
Project-URL: Bug Tracker, https://github.com/jashvira/reddit-consensus/issues
Keywords: reddit,ai,agent,recommendations,consensus,community
Classifier: Development Status :: 4 - Beta
Classifier: Intended Audience :: Developers
Classifier: Intended Audience :: End Users/Desktop
Classifier: Operating System :: OS Independent
Classifier: Programming Language :: Python :: 3
Classifier: Programming Language :: Python :: 3.11
Classifier: Programming Language :: Python :: 3.12
Classifier: Topic :: Software Development :: Libraries :: Python Modules
Classifier: Topic :: Internet :: WWW/HTTP :: Dynamic Content
Classifier: Topic :: Scientific/Engineering :: Artificial Intelligence
Requires-Python: >=3.11
License-File: LICENSE
Requires-Dist: openai>=1.88.0
Requires-Dist: asyncpraw>=7.7.1
Requires-Dist: rich>=13.0.0
Provides-Extra: notebook
Requires-Dist: ipykernel>=6.29.5; extra == "notebook"
Requires-Dist: ipywidgets>=8.1.7; extra == "notebook"
Dynamic: license-file
